setup.py
coyote/__init__.py
coyote/coyote.py
coyote.egg-info/PKG-INFO
coyote.egg-info/SOURCES.txt
coyote.egg-info/dependency_links.txt
coyote.egg-info/top_level.txt