Metadata-Version: 1.0
Name: coyote
Version: 0.0.0
Summary: An attempt to make a Chaos Monkey like framework in Python
Home-page: https://github.com/charlesthomas/coyote
Author: Charles Thomas
Author-email: ch@rlesthom.as
License: The MIT License (MIT)
